shorturls/__init__.py
shorturls/models.py
shorturls/urls.py
shorturls/views.py
shorturls/migrations/0001_initial.py
shorturls/migrations/__init__.py
shorturls/utils/__init__.py
shorturls/utils/nonce.py
shorturls/utils/shortcuts.py
shorturls-0.0.1.dist-info/DESCRIPTION.rst
shorturls-0.0.1.dist-info/METADATA
shorturls-0.0.1.dist-info/RECORD
shorturls-0.0.1.dist-info/WHEEL
shorturls-0.0.1.dist-info/metadata.json
shorturls-0.0.1.dist-info/top_level.txt
tests/__init__.py
tests/test_models.py
tests/test_utils.py
tests/test_views.py
