Metadata-Version: 2.0
Name: shorturls
Version: 0.0.1
Summary: Short URLs service for OpenTherapeutics.
Home-page: https://github.com/OpenTherapeutics/shorturls
Author: Open Therapeutics
Author-email: mkoistinen@opentherapeutics.org
License: MIT License
Platform: any
Classifier: Environment :: Web Environment
Classifier: Framework :: Django
Classifier: Framework :: Django :: 1.10
Classifier: License :: OSI Approved :: MIT License
Classifier: Programming Language :: Python
Classifier: Programming Language :: Python :: 3
Classifier: Programming Language :: Python :: 3.5
Requires-Dist: pycrypto (>-2.6.1)
Requires-Dist: Django (>=1.10,<1.11)
